__init__.py
kardb_local.py
kardb_mysql.py
kardb-0.0.2.dist-info/LICENSE
kardb-0.0.2.dist-info/METADATA
kardb-0.0.2.dist-info/WHEEL
kardb-0.0.2.dist-info/top_level.txt
kardb-0.0.2.dist-info/RECORD
